MANIFEST.in
README.rst
setup.cfg
setup.py
AlgoLib.egg-info/PKG-INFO
AlgoLib.egg-info/SOURCES.txt
AlgoLib.egg-info/dependency_links.txt
AlgoLib.egg-info/entry_points.txt
AlgoLib.egg-info/top_level.txt
algolib/__init__.py