Metadata-Version: 1.1
Name: AlgoLib
Version: 0.9.4
Summary: AlgoLib Project
Home-page: UNKNOWN
Author: AlgoFund
Author-email: a.mostajabi1994@gmail.com
License: AlgoFund
Keywords: packaging example
Platform: UNKNOWN
Classifier: Development Status :: 3 - Alpha
Classifier: Intended Audience :: Developers
Classifier: Topic :: Software Development :: Build Tools
Classifier: Programming Language :: Python :: 3.6
